pymetro/__init__.py
pymetro/pymetro.py
pymetro-0.27.dist-info/LICENSE
pymetro-0.27.dist-info/METADATA
pymetro-0.27.dist-info/WHEEL
pymetro-0.27.dist-info/top_level.txt
pymetro-0.27.dist-info/RECORD
