Metadata-Version: 2.1
Name: pymetro
Version: 0.27
Summary: A library for formatting numbers according to the metric system
Home-page: https://github.com/baselkorj/pymetro
Author: Abdulrhman-AIG, baselkorj
Author-email: abdalrhman.ib1998@gmail.com, baselanwarkorj@gmail.com
License: GPL-3.0
Download-URL: https://github.com/user/pymetro/archive/pymetro_v02.tar.gz
Keywords: Units,Metric,Scientific Notation,SI
Platform: UNKNOWN
Classifier: Development Status :: 4 - Beta
Classifier: Intended Audience :: Science/Research
Classifier: Topic :: Scientific/Engineering
Classifier: License :: OSI Approved :: GNU General Public License v3 (GPLv3)
Classifier: Programming Language :: Python :: 3.7
Classifier: Programming Language :: Python :: 3.8
Classifier: Programming Language :: Python :: 3.9
